dataclassabc/__init__.py
dataclass_abc-0.0.8.dist-info/LICENSE
dataclass_abc-0.0.8.dist-info/METADATA
dataclass_abc-0.0.8.dist-info/WHEEL
dataclass_abc-0.0.8.dist-info/top_level.txt
dataclass_abc-0.0.8.dist-info/RECORD
