Metadata-Version: 2.1
Name: dataclass-abc
Version: 0.0.8
Summary: Library that lets you define abstract properties for dataclasses.
Home-page: https://github.com/MichaelSchneeberger/dataclass-abc
Author: Michael Schneeberger
Author-email: michael.schneeb@outlook.com
Keywords: dataclass-abc abstract abc property
Classifier: License :: OSI Approved :: MIT License
Classifier: Programming Language :: Python :: 3.11
Requires-Python: >=3.10
License-File: LICENSE
